file_signature_validation/__init__.py
fleep/__init__.py
fleep/data.json
file_signature_validation-0.9.0.dist-info/LICENSE
file_signature_validation-0.9.0.dist-info/METADATA
file_signature_validation-0.9.0.dist-info/WHEEL
file_signature_validation-0.9.0.dist-info/top_level.txt
file_signature_validation-0.9.0.dist-info/RECORD
