Metadata-Version: 2.1
Name: file_signature_validation
Version: 0.9.0
Summary: File validation based on file signature.
License: MIT License
Project-URL: Homepage, https://github.com/overnitecbt/file_signature_validation
Keywords: file,validation
Classifier: License :: OSI Approved :: MIT License
Classifier: Programming Language :: Python
Classifier: Programming Language :: Python :: 3
Requires-Python: >=3.10
License-File: LICENSE
Requires-Dist: requests
